fastal/__init__.py
fastal/langgraph/__init__.py
fastal/langgraph/toolkit/__init__.py
fastal/langgraph/toolkit/exceptions.py
fastal/langgraph/toolkit/memory/__init__.py
fastal/langgraph/toolkit/memory/summary.py
fastal/langgraph/toolkit/models/__init__.py
fastal/langgraph/toolkit/models/base.py
fastal/langgraph/toolkit/models/config.py
fastal/langgraph/toolkit/models/factory.py
fastal/langgraph/toolkit/models/types.py
fastal/langgraph/toolkit/models/providers/__init__.py
fastal/langgraph/toolkit/models/providers/embeddings/__init__.py
fastal/langgraph/toolkit/models/providers/embeddings/bedrock.py
fastal/langgraph/toolkit/models/providers/embeddings/ollama.py
fastal/langgraph/toolkit/models/providers/embeddings/openai.py
fastal/langgraph/toolkit/models/providers/llm/__init__.py
fastal/langgraph/toolkit/models/providers/llm/anthropic.py
fastal/langgraph/toolkit/models/providers/llm/bedrock.py
fastal/langgraph/toolkit/models/providers/llm/ollama.py
fastal/langgraph/toolkit/models/providers/llm/openai.py
fastal/langgraph/toolkit/models/providers/stt/__init__.py
fastal/langgraph/toolkit/models/providers/stt/azure.py
fastal/langgraph/toolkit/models/providers/stt/google.py
fastal/langgraph/toolkit/models/providers/stt/openai.py
fastal/langgraph/toolkit/models/providers/tts/__init__.py
fastal/langgraph/toolkit/models/providers/tts/azure.py
fastal/langgraph/toolkit/models/providers/tts/elevenlabs.py
fastal/langgraph/toolkit/models/providers/tts/google.py
fastal/langgraph/toolkit/models/providers/tts/openai.py
fastal_langgraph_toolkit-0.4.1.dist-info/METADATA
fastal_langgraph_toolkit-0.4.1.dist-info/WHEEL
fastal_langgraph_toolkit-0.4.1.dist-info/licenses/LICENSE
fastal_langgraph_toolkit-0.4.1.dist-info/RECORD
