Metadata-Version: 2.4
Name: fastal-langgraph-toolkit
Version: 0.4.1
Summary: Common utilities and tools for LangGraph agents by Fastal
Project-URL: Homepage, https://github.com/FastalGroup/fastal-langgraph-toolkit
Project-URL: Repository, https://github.com/FastalGroup/fastal-langgraph-toolkit.git
Project-URL: Issues, https://github.com/FastalGroup/fastal-langgraph-toolkit/issues
Author-email: Stefano Capezzone <stefano@capezzone.it>
License: MIT
License-File: LICENSE
Keywords: agents,ai,langchain,langgraph,toolkit
Classifier: Development Status :: 4 - Beta
Classifier: Intended Audience :: Developers
Classifier: License :: OSI Approved :: MIT License
Classifier: Programming Language :: Python :: 3
Classifier: Programming Language :: Python :: 3.10
Classifier: Programming Language :: Python :: 3.11
Classifier: Programming Language :: Python :: 3.12
Classifier: Topic :: Scientific/Engineering :: Artificial Intelligence
Classifier: Topic :: Software Development :: Libraries :: Python Modules
Requires-Python: >=3.10
Requires-Dist: langchain-core>=0.1
Requires-Dist: langgraph>=0.1
Requires-Dist: pydantic-settings>=2.0
Requires-Dist: pydantic>=2.0
Provides-Extra: all
Requires-Dist: boto3>=1.26; extra == 'all'
Requires-Dist: langchain-anthropic>=0.1; extra == 'all'
Requires-Dist: langchain-aws>=0.1; extra == 'all'
Requires-Dist: langchain-ollama>=0.1; extra == 'all'
Requires-Dist: langchain-openai>=0.2; extra == 'all'
Requires-Dist: openai>=1.54.0; extra == 'all'
Provides-Extra: anthropic
Requires-Dist: langchain-anthropic>=0.1; extra == 'anthropic'
Provides-Extra: bedrock
Requires-Dist: boto3>=1.26; extra == 'bedrock'
Requires-Dist: langchain-aws>=0.1; extra == 'bedrock'
Provides-Extra: ollama
Requires-Dist: langchain-ollama>=0.1; extra == 'ollama'
Provides-Extra: openai
Requires-Dist: langchain-openai>=0.2; extra == 'openai'
Requires-Dist: openai>=1.54.0; extra == 'openai'
Provides-Extra: stt
Requires-Dist: openai>=1.54.0; extra == 'stt'
